setup.cfg
setup.py
gooeypip/__init__.py
gooeypip/gooey.py
gooeypip.egg-info/PKG-INFO
gooeypip.egg-info/SOURCES.txt
gooeypip.egg-info/dependency_links.txt
gooeypip.egg-info/top_level.txt
gooeypip/grammar/__init__.py
gooeypip/grammar/attributes.py
gooeypip/grammar/statements.py
gooeypip/interpreter/__init__.py
gooeypip/interpreter/actionbuttons.py
gooeypip/interpreter/interpreter.py
gooeypip/interpreter/matrix.py
gooeypip/pypeg2/__init__.py
gooeypip/pypeg2/xmlast.py
gooeypip/pypeg2/test/__init__.py
gooeypip/pypeg2/test/test_pypeg2.py
gooeypip/pypeg2/test/test_xmlast.py