Metadata-Version: 1.1
Name: gooeypip
Version: 0.5
Summary: Gooey Language
Home-page: https://github.com/harrise/gooey-pip
Author: Gooey Comps
Author-email: harrise@carleton.edu
License: UNKNOWN
Download-URL: https://github.com/harrise/gooey-pip/tarball/0.5
Keywords: gui
Platform: UNKNOWN
